bisocket/__init__.py
bisocket/main.py
bisocket/cython/c_main.c
bisocket/cython/c_main.cpython-312-darwin.so
bisocket/cython/c_main.pyx
bisocket-0.0.5.dist-info/licenses/LICENSE
bisocket-0.0.5.dist-info/METADATA
bisocket-0.0.5.dist-info/WHEEL
bisocket-0.0.5.dist-info/top_level.txt
bisocket-0.0.5.dist-info/RECORD
