Metadata-Version: 2.4
Name: bisocket
Version: 0.0.5
Summary: bisocket is a high-level Python library for simple, secure, and truly bidirectional socket communication, using a dual-socket architecture to enable non-blocking, full-duplex I/O. It provides automatic AES-GCM encryption and supports both synchronous (threading) and asynchronous (asyncio) client-server applications
Home-page: 
Author: Daniel Olson
Author-email: daniel@orphos.cloud
Keywords: socket bidirectional
Classifier: Development Status :: 3 - Alpha
Classifier: Intended Audience :: Developers
Classifier: License :: OSI Approved :: MIT License
Classifier: Operating System :: OS Independent
Classifier: Programming Language :: Python :: 3
Classifier: Programming Language :: Python :: 3.10
Classifier: Programming Language :: Python :: 3.11
Classifier: Programming Language :: Python :: 3.12
Requires-Python: >=3.10
License-File: LICENSE
Requires-Dist: cryptography
Dynamic: author
Dynamic: author-email
Dynamic: classifier
Dynamic: description
Dynamic: description-content-type
Dynamic: keywords
Dynamic: license-file
Dynamic: requires-dist
Dynamic: requires-python
Dynamic: summary
